njnuko/__init__.py
njnuko/tools/__init__.py
njnuko/tools/check_files.py
njnuko/tools/check_files1.py
njnuko/tools/find_regex_in_folder.py
njnuko/tools/get_ss_accounts.py
njnuko/tools/keyboard_win.py
njnuko/tools/ms-pg-sql.py
njnuko/tools/open_port.py
njnuko/tools/portscan.py
njnuko/tools/regex_sample.py
njnuko/tools/sender_o365.py
njnuko/tools/testing_time.py
njnuko/tools/urlopen_auth.py
njnuko/tools/watermark.py
njnuko/tools/wechat.py
njnuko-5.2.1.dist-info/LICENSE
njnuko-5.2.1.dist-info/METADATA
njnuko-5.2.1.dist-info/WHEEL
njnuko-5.2.1.dist-info/top_level.txt
njnuko-5.2.1.dist-info/RECORD
