Metadata-Version: 2.1
Name: njnuko
Version: 5.2.1
Summary: njnuko tools,need to install sudo apt install exiftool
Home-page: https://github.com/njnuko/njnuko
Author: njnuko
Author-email: njnuko@163.com
License: MIT
Keywords: files sorting
License-File: LICENSE
Requires-Dist: imagehash
Requires-Dist: requests
Requires-Dist: Pillow
Requires-Dist: pyexiftool==0.4.13
Requires-Dist: iptools
